lib/__init__.py
lib_elem_isotopes-0.1.0.dist-info/LICENSE
lib_elem_isotopes-0.1.0.dist-info/METADATA
lib_elem_isotopes-0.1.0.dist-info/WHEEL
lib_elem_isotopes-0.1.0.dist-info/top_level.txt
lib_elem_isotopes-0.1.0.dist-info/RECORD
