Metadata-Version: 2.1
Name: lib-elem-isotopes
Version: 0.1.0
Summary: Dealing with isotopic inventories.
Home-page: https://github.com/kaasknak/lib
Author: kaasknak
Author-email: private@mail.com
License: UNKNOWN
Platform: UNKNOWN
Classifier: Programming Language :: Python :: 3
Classifier: License :: OSI Approved :: MIT License
Classifier: Operating System :: OS Independent
Requires-Python: >=3.6
